{
  "looped":false,
  "manualFov":false,
  "markers":[
    {
      "fov":50,
      "movingEnd":false,
      "movingStart":false,
      "pos":{
        "x":507.8123779,
        "y":714.3429565,
        "z":117.8309097
      },
      "rot":{
        "z":-0.7934553623,
        "w":0.608065486,
        "x":0.01592061669,
        "y":0.02077457681
      },
      "time":0,
      "trackPosition":false
    },
    {
      "fov":50,
      "movingEnd":false,
      "movingStart":false,
      "pos":{
        "x":511.783905,
        "y":715.6184692,
        "z":118.1847229
      },
      "rot":{
        "z":-0.8175368309,
        "w":0.575281322,
        "x":0.01506224927,
        "y":0.02140508778
      },
      "time":5,
      "trackPosition":false
    },
    {
      "fov":50,
      "movingEnd":false,
      "movingStart":false,
      "pos":{
        "x":513.3106689,
        "y":716.892334,
        "z":118.3443909
      },
      "rot":{
        "z":-0.8403790593,
        "w":0.5405180454,
        "x":0.02165932581,
        "y":0.03367517889
      },
      "time":6,
      "trackPosition":false
    },
    {
      "fov":50,
      "movingEnd":false,
      "movingStart":false,
      "pos":{
        "x":509.3662109,
        "y":724.1115112,
        "z":118.6431046
      },
      "rot":{
        "z":-0.9176343679,
        "w":0.3965006471,
        "x":0.01074832864,
        "y":0.02487520687
      },
      "time":9,
      "trackPosition":false
    },
    {
      "fov":50,
      "movingEnd":false,
      "movingStart":false,
      "pos":{
        "x":507.7333679,
        "y":731.5908813,
        "z":119.3247452
      },
      "rot":{
        "z":-0.9731345177,
        "w":0.2300397605,
        "x":0.002191925654,
        "y":0.00927247759
      },
      "time":12,
      "trackPosition":false
    },
    {
      "fov":50,
      "movingEnd":false,
      "movingStart":false,
      "pos":{
        "x":477.018219,
        "y":714.3847046,
        "z":119.8309631
      },
      "rot":{
        "z":-0.9487760067,
        "w":-0.3125081658,
        "x":-0.01454975456,
        "y":0.04417310283
      },
      "time":17,
      "trackPosition":false
    },
    {
      "fov":50,
      "movingEnd":false,
      "movingStart":false,
      "pos":{
        "x":454.9881287,
        "y":694.4575195,
        "z":119.1639557
      },
      "rot":{
        "z":-0.5742013454,
        "w":-0.8138675094,
        "x":-0.07268355787,
        "y":0.0512798503
      },
      "time":22,
      "trackPosition":false
    },
    {
      "fov":50,
      "movingEnd":false,
      "movingStart":false,
      "pos":{
        "x":455.5781555,
        "y":694.8405762,
        "z":118.792984
      },
      "rot":{
        "z":-0.6045167446,
        "w":-0.7928651571,
        "x":-0.06120852754,
        "y":0.04666818306
      },
      "time":27,
      "trackPosition":false
    },
    {
      "fov":50,
      "movingEnd":false,
      "movingStart":false,
      "pos":{
        "x":456.1407776,
        "y":693.2020874,
        "z":118.5346375
      },
      "rot":{
        "z":-0.4733410776,
        "w":-0.8804968596,
        "x":-0.02285890654,
        "y":0.01228858624
      },
      "time":32,
      "trackPosition":false
    },
    {
      "fov":50,
      "movingEnd":false,
      "movingStart":false,
      "pos":{
        "x":458.194458,
        "y":692.3035278,
        "z":118.4411621
      },
      "rot":{
        "z":-0.2217229605,
        "w":-0.9727120996,
        "x":-0.06663024426,
        "y":0.01518790424
      },
      "time":39,
      "trackPosition":false
    }
  ],
  "name":"AI Race - Highway Loop 1",
  "rotFixId":9,
  "version":"6"
}