{
  "description":"Description of theses Sites. Contains Locations and Zones.",
  "dir":"/levels/west_coast_usa/",
  "filename":"facilities.sites.json",
  "locations":{},
  "name":"facilities.sites.json",
  "parkingSpots":[
    {
      "color":[
        1,
        1,
        1
      ],
      "customFields":{
        "names":{},
        "tags":{},
        "types":{},
        "values":{}
      },
      "isMultiSpot":false,
      "name":"serviceStationParking1",
      "oldId":1836,
      "pos":[
        904.4869385,
        -546.2740479,
        163.8014374
      ],
      "rot":[
        0,
        0,
        0.748227477,
        0.663442314
      ],
      "scl":[
        2.5,
        6,
        3.538806081
      ],
      "spotAmount":1,
      "spotDirection":"Left",
      "spotOffset":0,
      "spotRotation":0
    },
    {
      "color":[
        1,
        1,
        1
      ],
      "customFields":{
        "names":{},
        "tags":{},
        "types":{},
        "values":{}
      },
      "isMultiSpot":false,
      "name":"serviceStationParking2",
      "oldId":1837,
      "pos":[
        910.5483398,
        -522.1712646,
        163.4891052
      ],
      "rot":[
        0.001151475914,
        -0.0003839234897,
        -0.7511225522,
        -0.6601618893
      ],
      "scl":[
        7.187660044,
        23.60298804,
        6.499732018
      ],
      "spotAmount":1,
      "spotDirection":"Left",
      "spotOffset":0,
      "spotRotation":0
    },
    {
      "color":[
        1,
        1,
        1
      ],
      "customFields":{
        "names":{},
        "tags":{},
        "types":{},
        "values":{}
      },
      "isMultiSpot":false,
      "name":"belascoAuto1",
      "oldId":1838,
      "pos":[
        -698.602356,
        808.687439,
        74.85501099
      ],
      "rot":[
        0,
        0,
        -0.3826834276,
        -0.9238794419
      ],
      "scl":[
        3.8823241,
        6.958008528,
        3
      ],
      "spotAmount":1,
      "spotDirection":"Left",
      "spotOffset":0,
      "spotRotation":0
    },
    {
      "color":[
        1,
        1,
        1
      ],
      "customFields":{
        "names":{},
        "tags":{},
        "types":{},
        "values":{}
      },
      "isMultiSpot":false,
      "name":"belascoAuto2",
      "oldId":1839,
      "pos":[
        -702.3754272,
        809.4387817,
        74.85502625
      ],
      "rot":[
        0.00368527401,
        -0.001495011658,
        0.3759141188,
        0.9266459728
      ],
      "scl":[
        11.031425,
        22.2890625,
        3
      ],
      "spotAmount":1,
      "spotDirection":"Left",
      "spotOffset":0,
      "spotRotation":0
    },
    {
      "color":[
        1,
        1,
        1
      ],
      "customFields":{
        "names":{},
        "tags":{},
        "types":{},
        "values":{}
      },
      "isMultiSpot":false,
      "name":"jerryRigs1",
      "oldId":1840,
      "pos":[
        -68.03170013,
        2.583500147,
        119.830246
      ],
      "rot":[
        0,
        0,
        0.9161097108,
        -0.4009275915
      ],
      "scl":[
        2.5,
        6,
        3
      ],
      "spotAmount":1,
      "spotDirection":"Left",
      "spotOffset":0,
      "spotRotation":0
    },
    {
      "color":[
        1,
        1,
        1
      ],
      "customFields":{
        "names":{},
        "tags":{},
        "types":{},
        "values":{}
      },
      "isMultiSpot":false,
      "name":"garageDealership1",
      "oldId":1841,
      "pos":[
        836.3638916,
        -535.3862305,
        165.1521759
      ],
      "rot":[
        0.002731130585,
        0.0009946844612,
        -0.7095405583,
        -0.7046585372
      ],
      "scl":[
        2.5,
        6,
        3
      ],
      "spotAmount":1,
      "spotDirection":"Left",
      "spotOffset":0,
      "spotRotation":0
    },
    {
      "color":[
        1,
        1,
        1
      ],
      "customFields":{
        "names":{},
        "tags":{},
        "types":{},
        "values":{}
      },
      "isMultiSpot":false,
      "name":"richsparking1",
      "oldId":1842,
      "pos":[
        -820.6811523,
        905.0333862,
        74.86978149
      ],
      "rot":[
        0,
        0,
        0.7087229864,
        0.7054869588
      ],
      "scl":[
        2.5,
        6,
        3
      ],
      "spotAmount":1,
      "spotDirection":"Left",
      "spotOffset":0,
      "spotRotation":0
    },
    {
      "color":[
        1,
        1,
        1
      ],
      "customFields":{
        "names":{},
        "tags":{},
        "types":{},
        "values":{}
      },
      "isMultiSpot":false,
      "name":"jeffersonparking1",
      "oldId":1843,
      "pos":[
        -393.4327393,
        178.1012878,
        100.7432632
      ],
      "rot":[
        0.002251100662,
        0.01182956006,
        0.9779105526,
        -0.2086771177
      ],
      "scl":[
        2.5,
        6,
        3
      ],
      "spotAmount":1,
      "spotDirection":"Left",
      "spotOffset":0,
      "spotRotation":0
    },
    {
      "color":[
        1,
        1,
        1
      ],
      "customFields":{
        "names":{},
        "tags":{},
        "types":{},
        "values":{}
      },
      "isMultiSpot":false,
      "name":"commercialGarageParking2",
      "oldId":1844,
      "pos":[
        -220.350647,
        -27.5606575,
        120.9462891
      ],
      "rot":[
        0,
        0,
        0.6578822136,
        0.7531207204
      ],
      "scl":[
        5.069174587,
        16.72308441,
        9.897033691
      ],
      "spotAmount":1,
      "spotDirection":"Left",
      "spotOffset":0,
      "spotRotation":0
    },
    {
      "color":[
        1,
        1,
        1
      ],
      "customFields":{
        "names":{},
        "tags":{},
        "types":{},
        "values":{}
      },
      "isMultiSpot":false,
      "name":"commercialGarageParking1",
      "oldId":1845,
      "pos":[
        -199.0617676,
        -34.54320145,
        120.9080353
      ],
      "rot":[
        0.003828659862,
        -0.003360743063,
        0.659681034,
        0.7515285306
      ],
      "scl":[
        2.5,
        6,
        3.788818359
      ],
      "spotAmount":1,
      "spotDirection":"Left",
      "spotOffset":0,
      "spotRotation":0
    },
    {
      "color":[
        1,
        1,
        1
      ],
      "customFields":{
        "names":{},
        "tags":{},
        "types":{},
        "values":{}
      },
      "isMultiSpot":false,
      "name":"truckShop1",
      "oldId":1846,
      "pos":[
        -247.9966583,
        -40.92715454,
        120.790329
      ],
      "rot":[
        -0.00234686608,
        0.003625264915,
        0.9985765162,
        0.05316199458
      ],
      "scl":[
        4.351467227,
        10.87371826,
        5.436859131
      ],
      "spotAmount":1,
      "spotDirection":"Left",
      "spotOffset":0,
      "spotRotation":0
    },
    {
      "color":[
        1,
        1,
        1
      ],
      "customFields":{
        "names":{},
        "tags":{},
        "types":{},
        "values":{}
      },
      "isMultiSpot":false,
      "name":"commercialGarageParkingOutside4",
      "oldId":1847,
      "pos":[
        -283.2748718,
        -82.74004364,
        119.3900604
      ],
      "rot":[
        0,
        0,
        0.7310373348,
        -0.6823373435
      ],
      "scl":[
        3.756834865,
        16.18706781,
        13.57785702
      ],
      "spotAmount":4,
      "spotDirection":"Left",
      "spotOffset":0.8090000153,
      "spotRotation":0
    },
    {
      "color":[
        1,
        1,
        1
      ],
      "customFields":{
        "names":{},
        "tags":{},
        "types":{},
        "values":{}
      },
      "isMultiSpot":false,
      "name":"commercialGarageParkingOutside3",
      "oldId":1848,
      "pos":[
        -283.5862427,
        -78.38955688,
        119.3900528
      ],
      "rot":[
        0,
        0,
        0.7316126391,
        -0.6817204356
      ],
      "scl":[
        4.064909935,
        16.18000031,
        14.06167603
      ],
      "spotAmount":1,
      "spotDirection":"Left",
      "spotOffset":0,
      "spotRotation":0
    },
    {
      "color":[
        1,
        1,
        1
      ],
      "customFields":{
        "names":{},
        "tags":{},
        "types":{},
        "values":{}
      },
      "isMultiSpot":false,
      "name":"commercialGarageParkingOutside2",
      "oldId":1849,
      "pos":[
        -283.8959656,
        -73.97385406,
        119.4012833
      ],
      "rot":[
        0,
        0,
        0.7360778033,
        -0.6768968119
      ],
      "scl":[
        3.996153831,
        16.18700027,
        12.93488216
      ],
      "spotAmount":1,
      "spotDirection":"Left",
      "spotOffset":0,
      "spotRotation":0
    },
    {
      "color":[
        1,
        1,
        1
      ],
      "customFields":{
        "names":{},
        "tags":{},
        "types":{},
        "values":{}
      },
      "isMultiSpot":false,
      "name":"commercialGarageParkingOutside1",
      "oldId":1850,
      "pos":[
        -284.2545776,
        -69.42679596,
        119.4356308
      ],
      "rot":[
        0,
        -0,
        -0.732225864,
        0.681061969
      ],
      "scl":[
        4.060256958,
        16.18700027,
        14.54558659
      ],
      "spotAmount":1,
      "spotDirection":"Left",
      "spotOffset":0,
      "spotRotation":0
    },
    {
      "color":[
        1,
        1,
        1
      ],
      "customFields":{
        "names":{},
        "tags":{},
        "types":{},
        "values":{}
      },
      "isMultiSpot":false,
      "name":"garageDealership2",
      "oldId":1851,
      "pos":[
        828.3341675,
        -513.5930176,
        165.168808
      ],
      "rot":[
        0.0001876067209,
        -0.0001906656784,
        0.7128015766,
        0.7013656969
      ],
      "scl":[
        5,
        15,
        4
      ],
      "spotAmount":1,
      "spotDirection":"Left",
      "spotOffset":0,
      "spotRotation":0
    },
    {
      "color":[
        1,
        1,
        1
      ],
      "customFields":{
        "names":{},
        "tags":{},
        "types":{},
        "values":{}
      },
      "isMultiSpot":false,
      "name":"dragPaddockPark1",
      "oldId":1852,
      "pos":[
        -224.1972504,
        -210.230484,
        118.859642
      ],
      "rot":[
        0,
        0,
        0.4592789654,
        0.8882920569
      ],
      "scl":[
        2.5,
        6,
        3
      ],
      "spotAmount":1,
      "spotDirection":"Left",
      "spotOffset":0,
      "spotRotation":0
    },
    {
      "color":[
        1,
        1,
        1
      ],
      "customFields":{
        "names":{},
        "tags":{},
        "types":{},
        "values":{}
      },
      "isMultiSpot":false,
      "name":"dragPaddockPark2",
      "oldId":1853,
      "pos":[
        -220.9319611,
        -214.4823456,
        118.8203354
      ],
      "rot":[
        0,
        0,
        0.4508538246,
        0.8925978541
      ],
      "scl":[
        2.5,
        6,
        3
      ],
      "spotAmount":1,
      "spotDirection":"Left",
      "spotOffset":0,
      "spotRotation":0
    },
    {
      "color":[
        1,
        1,
        1
      ],
      "customFields":{
        "names":{},
        "tags":{},
        "types":{},
        "values":{}
      },
      "isMultiSpot":false,
      "name":"dragPaddockPark3",
      "oldId":1854,
      "pos":[
        -207.4669189,
        -197.3882599,
        119.1350708
      ],
      "rot":[
        0,
        0,
        0.8910026231,
        -0.4539984934
      ],
      "scl":[
        3.25,
        8,
        4
      ],
      "spotAmount":1,
      "spotDirection":"Left",
      "spotOffset":0,
      "spotRotation":0
    },
    {
      "color":[
        1,
        1,
        1
      ],
      "customFields":{
        "names":{},
        "tags":{},
        "types":{},
        "values":{}
      },
      "isMultiSpot":false,
      "name":"fastAutomotiveParking",
      "oldId":1855,
      "pos":[
        292.7936401,
        -162.4657288,
        143.8878632
      ],
      "rot":[
        0,
        0,
        -0.7067754332,
        -0.7074382886
      ],
      "scl":[
        2.5,
        6,
        3
      ],
      "spotAmount":1,
      "spotDirection":"Left",
      "spotOffset":0,
      "spotRotation":0
    },
    {
      "color":[
        1,
        1,
        1
      ],
      "customFields":{
        "names":{},
        "tags":{},
        "types":{},
        "values":{}
      },
      "isMultiSpot":false,
      "name":"policeDealerParking",
      "oldId":1856,
      "pos":[
        -756.4741211,
        740.9037476,
        81.831604
      ],
      "rot":[
        0,
        0,
        -0.7124267877,
        -0.7017467092
      ],
      "scl":[
        2.5,
        6,
        3
      ],
      "spotAmount":1,
      "spotDirection":"Left",
      "spotOffset":0,
      "spotRotation":0
    },
    {
      "color":[
        1,
        1,
        1
      ],
      "customFields":{
        "names":{},
        "tags":{},
        "types":{},
        "values":{}
      },
      "isMultiSpot":false,
      "name":"serviceDealerParking",
      "oldId":1857,
      "pos":[
        -756.4824829,
        748.9685059,
        81.82583618
      ],
      "rot":[
        0,
        0,
        0.7031282324,
        0.711063267
      ],
      "scl":[
        2.5,
        6,
        3
      ],
      "spotAmount":1,
      "spotDirection":"Left",
      "spotOffset":0,
      "spotRotation":0
    },
    {
      "color":[
        1,
        1,
        1
      ],
      "customFields":{
        "names":{},
        "tags":{},
        "types":{},
        "values":{}
      },
      "isMultiSpot":false,
      "name":"trailerShop",
      "oldId":1858,
      "pos":[
        -203.3486786,
        -17.31359863,
        120.8540878
      ],
      "rot":[
        0,
        0,
        0.6637087559,
        0.7479913467
      ],
      "scl":[
        4,
        14,
        8
      ],
      "spotAmount":1,
      "spotDirection":"Left",
      "spotOffset":0,
      "spotRotation":0
    },
    {
      "color":[
        1,
        1,
        1
      ],
      "customFields":{
        "names":{},
        "tags":{},
        "types":{},
        "values":{}
      },
      "isMultiSpot":false,
      "name":"frameDealershipParking",
      "oldId":1859,
      "pos":[
        -622.2583008,
        105.0634918,
        102.1436691
      ],
      "rot":[
        0,
        0,
        -0.3875311374,
        -0.9218567638
      ],
      "scl":[
        4,
        14,
        8
      ],
      "spotAmount":1,
      "spotDirection":"Left",
      "spotOffset":0,
      "spotRotation":0
    },
    {
      "color":[
        1,
        1,
        1
      ],
      "customFields":{
        "names":{},
        "tags":{},
        "types":{},
        "values":{}
      },
      "isMultiSpot":false,
      "name":"illegalDealershipParking",
      "oldId":1860,
      "pos":[
        334.3110352,
        1544.787109,
        74.66395569
      ],
      "rot":[
        0,
        0,
        0.2309501323,
        -0.9729657459
      ],
      "scl":[
        3.25,
        8,
        4
      ],
      "spotAmount":1,
      "spotDirection":"Left",
      "spotOffset":0,
      "spotRotation":0
    },
    {
      "color":[
        1,
        1,
        1
      ],
      "customFields":{
        "names":{},
        "tags":{},
        "types":{},
        "values":{}
      },
      "isMultiSpot":false,
      "name":"offroadDealershipParking",
      "oldId":1861,
      "pos":[
        528.152771,
        -81.9838562,
        146.5817871
      ],
      "rot":[
        0,
        0,
        0.7208619181,
        0.6930785232
      ],
      "scl":[
        3.25,
        8,
        4
      ],
      "spotAmount":1,
      "spotDirection":"Left",
      "spotOffset":0,
      "spotRotation":0
    },
    {
      "color":[
        1,
        1,
        1
      ],
      "customFields":{
        "names":{},
        "tags":{},
        "types":{},
        "values":{}
      },
      "isMultiSpot":false,
      "name":"dragDealershipParking",
      "oldId":1862,
      "pos":[
        315.8274231,
        -136.2704468,
        143.8878479
      ],
      "rot":[
        0,
        0,
        0.9999883175,
        -0.004842934199
      ],
      "scl":[
        2.5,
        6,
        3
      ],
      "spotAmount":1,
      "spotDirection":"Left",
      "spotOffset":0,
      "spotRotation":0
    },
    {
      "color":[
        1,
        1,
        1
      ],
      "customFields":{
        "names":{},
        "tags":{},
        "types":{},
        "values":{}
      },
      "isMultiSpot":false,
      "name":"rallyDealershipParking",
      "oldId":1863,
      "pos":[
        312.6099854,
        -168.2041779,
        143.8878632
      ],
      "rot":[
        0,
        0,
        0.7082546314,
        -0.7059572955
      ],
      "scl":[
        2.5,
        6,
        3
      ],
      "spotAmount":1,
      "spotDirection":"Left",
      "spotOffset":0,
      "spotRotation":0
    },
    {
      "color":[
        1,
        1,
        1
      ],
      "customFields":{
        "names":{},
        "tags":{},
        "types":{},
        "values":{}
      },
      "isMultiSpot":false,
      "name":"discountDealershipParking",
      "oldId":1864,
      "pos":[
        -126.7744751,
        -39.35709763,
        119.8243866
      ],
      "rot":[
        0,
        0,
        -0.4747115085,
        -0.8801415368
      ],
      "scl":[
        2.5,
        6,
        3
      ],
      "spotAmount":1,
      "spotDirection":"Left",
      "spotOffset":0,
      "spotRotation":0
    },
    {
      "color":[
        1,
        1,
        1
      ],
      "customFields":{
        "names":{},
        "tags":{},
        "types":{},
        "values":{}
      },
      "isMultiSpot":false,
      "name":"onlineParking",
      "oldId":1865,
      "pos":[
        428.014679,
        1681.86792,
        74.73071289
      ],
      "rot":[
        0,
        0,
        -0.6954452367,
        -0.7185793099
      ],
      "scl":[
        3.25,
        8,
        4
      ],
      "spotAmount":1,
      "spotDirection":"Left",
      "spotOffset":0,
      "spotRotation":0
    },
    {
      "color":[
        1,
        1,
        1
      ],
      "customFields":{
        "names":{},
        "tags":{},
        "types":{},
        "values":{}
      },
      "isMultiSpot":false,
      "name":"onlineParkingBus",
      "oldId":1866,
      "pos":[
        430.9890747,
        1686.119019,
        74.66110229
      ],
      "rot":[
        0,
        0,
        0.6935629506,
        0.7203961568
      ],
      "scl":[
        4,
        14,
        8
      ],
      "spotAmount":1,
      "spotDirection":"Left",
      "spotOffset":0,
      "spotRotation":0
    },
    {
      "color":[
        1,
        1,
        1
      ],
      "customFields":{
        "names":{},
        "tags":{},
        "types":{},
        "values":{}
      },
      "isMultiSpot":false,
      "name":"chinatown_parking1",
      "oldId":1867,
      "pos":[
        -736.3143921,
        602.4072266,
        115.6663055
      ],
      "rot":[
        0,
        0,
        0,
        1
      ],
      "scl":[
        2.5,
        6,
        3
      ],
      "spotAmount":1,
      "spotDirection":"Left",
      "spotOffset":0,
      "spotRotation":0
    },
    {
      "color":[
        1,
        1,
        1
      ],
      "customFields":{
        "names":{},
        "tags":{},
        "types":{},
        "values":{}
      },
      "isMultiSpot":false,
      "name":"chinatown_parking2",
      "oldId":1868,
      "pos":[
        -733.5112305,
        602.2235718,
        115.662384
      ],
      "rot":[
        0,
        0,
        0,
        1
      ],
      "scl":[
        2.5,
        6,
        3
      ],
      "spotAmount":1,
      "spotDirection":"Left",
      "spotOffset":0,
      "spotRotation":0
    }
  ],
  "zones":[
    {
      "bot":{
        "active":false,
        "normal":[
          0,
          0,
          -1
        ],
        "pos":[
          0,
          0,
          -10
        ]
      },
      "color":[
        1,
        1,
        1
      ],
      "customFields":{
        "names":{},
        "tags":{},
        "types":{},
        "values":{}
      },
      "name":"servicestationGarage1",
      "oldId":1831,
      "top":{
        "active":false,
        "normal":[
          0,
          0,
          1
        ],
        "pos":[
          0,
          0,
          10
        ]
      },
      "vertices":[
        [
          924.0131836,
          -519.3427734,
          163.343399
        ],
        [
          922.880188,
          -528.2664185,
          163.5372314
        ],
        [
          897.6480713,
          -525.2210693,
          163.5436096
        ],
        [
          898.8135376,
          -516.215332,
          163.5436096
        ]
      ]
    },
    {
      "bot":{
        "active":false,
        "normal":[
          0,
          0,
          -1
        ],
        "pos":[
          0,
          0,
          -10
        ]
      },
      "color":[
        1,
        1,
        1
      ],
      "customFields":{
        "names":{},
        "tags":{},
        "types":{},
        "values":{}
      },
      "name":"servicestationGarage2",
      "oldId":1832,
      "top":{
        "active":false,
        "normal":[
          0,
          0,
          1
        ],
        "pos":[
          0,
          0,
          10
        ]
      },
      "vertices":[
        [
          897.461154,
          -548.611786,
          163.5436096
        ],
        [
          897.895527,
          -545.359167,
          163.5436096
        ],
        [
          898.329819,
          -542.085309,
          163.5436096
        ],
        [
          902.290181,
          -542.585294,
          163.5436096
        ],
        [
          906.262943,
          -542.975551,
          163.5436096
        ],
        [
          907.745563,
          -542.976759,
          163.5436096
        ],
        [
          909.027563,
          -542.576931,
          163.5436096
        ],
        [
          910.214155,
          -541.740512,
          163.5436096
        ],
        [
          911.171611,
          -540.355153,
          163.5436096
        ],
        [
          911.944004,
          -536.589499,
          163.5436096
        ],
        [
          912.417476,
          -532.397913,
          163.5436096
        ],
        [
          915.578526,
          -532.731955,
          163.5436096
        ],
        [
          918.793692,
          -533.2207,
          163.537735
        ],
        [
          918.400299,
          -537.307977,
          163.5424805
        ],
        [
          917.728102,
          -543.14956,
          163.5436096
        ],
        [
          917.301135,
          -545.008616,
          163.5436096
        ],
        [
          916.690643,
          -546.564473,
          163.5436096
        ],
        [
          915.800641,
          -547.856007,
          163.5436096
        ],
        [
          914.686044,
          -548.846024,
          163.5436096
        ],
        [
          913.2535,
          -549.65585,
          163.5436096
        ],
        [
          911.580887,
          -550.075471,
          163.5436096
        ],
        [
          909.777477,
          -550.126019,
          163.5436096
        ],
        [
          906.698661,
          -549.817376,
          163.5436096
        ],
        [
          903.619574,
          -549.437078,
          163.5436096
        ],
        [
          900.54124,
          -549.029983,
          163.5436096
        ]
      ]
    },
    {
      "bot":{
        "active":false,
        "normal":[
          0,
          0,
          -1
        ],
        "pos":[
          0,
          0,
          -10
        ]
      },
      "color":[
        1,
        1,
        1
      ],
      "customFields":{
        "names":{},
        "tags":{},
        "types":{},
        "values":{}
      },
      "name":"commercialGarage1",
      "oldId":1833,
      "top":{
        "active":false,
        "normal":[
          0,
          0,
          1
        ],
        "pos":[
          0,
          0,
          10
        ]
      },
      "vertices":[
        [
          -233.936203,
          -44.43613815,
          120.8573456
        ],
        [
          -234.0596838,
          -43.51412964,
          120.8573456
        ],
        [
          -240.3625622,
          -44.37031555,
          120.8573456
        ],
        [
          -241.1848259,
          -36.97226333,
          120.8137741
        ],
        [
          -235.0106278,
          -35.74295807,
          120.8573456
        ],
        [
          -236.8384095,
          -24.78937149,
          120.8311768
        ],
        [
          -197.3350677,
          -19.64664459,
          120.8841629
        ],
        [
          -194.6772766,
          -39.19102478,
          120.8442459
        ]
      ]
    },
    {
      "bot":{
        "active":false,
        "normal":[
          0,
          0,
          -1
        ],
        "pos":[
          0,
          0,
          -10
        ]
      },
      "color":[
        1,
        1,
        1
      ],
      "customFields":{
        "names":{},
        "tags":{},
        "types":{},
        "values":{}
      },
      "name":"dragPaddockGarage",
      "oldId":1834,
      "top":{
        "active":false,
        "normal":[
          0,
          0,
          1
        ],
        "pos":[
          0,
          0,
          10
        ]
      },
      "vertices":[
        [
          -221.7232971,
          -204.1242065,
          118.9034042
        ],
        [
          -231.6764679,
          -211.5038605,
          118.6885071
        ],
        [
          -224.3263702,
          -221.2561035,
          118.6916885
        ],
        [
          -214.4368744,
          -213.8125916,
          118.9058685
        ]
      ]
    },
    {
      "bot":{
        "active":false,
        "normal":[
          0,
          0,
          -1
        ],
        "pos":[
          0,
          0,
          -10
        ]
      },
      "color":[
        1,
        1,
        1
      ],
      "customFields":{
        "names":{},
        "tags":{},
        "types":{},
        "values":{}
      },
      "name":"chinatownGarage",
      "oldId":1835,
      "top":{
        "active":false,
        "normal":[
          0,
          0,
          1
        ],
        "pos":[
          0,
          0,
          10
        ]
      },
      "vertices":[
        [
          -727.8471069,
          598.585144,
          113.2155685
        ],
        [
          -727.8780518,
          605.6002197,
          115.7227631
        ],
        [
          -738.5219727,
          605.736145,
          112.7482681
        ],
        [
          -738.2688599,
          598.9611206,
          114.0600433
        ]
      ]
    },
    {
      "bot":{
        "active":false,
        "normal":[
          0,
          0,
          -1
        ],
        "pos":[
          0,
          0,
          -10
        ]
      },
      "color":[
        1,
        1,
        1
      ],
      "customFields":{
        "names":{},
        "tags":{},
        "types":{},
        "values":{}
      },
      "name":"cul-de-sacGarage",
      "oldId":2215,
      "top":{
        "active":false,
        "normal":[
          0,
          0,
          1
        ],
        "pos":[
          0,
          0,
          10
        ]
      },
      "vertices":[
        [
          -112.153038,
          -884.9197388,
          131.4678497
        ],
        [
          -124.4559555,
          -874.1381836,
          130.8634644
        ],
        [
          -135.1136932,
          -883.4789429,
          131.024765
        ],
        [
          -122.7306976,
          -899.1906738,
          131.2455902
        ]
      ]
    }
  ]
}