{
  "deliveryProviders":[
    {
      "id":"belascoGarage",
      "name":"Belasco Garage",
      "description":"Ships and receives car parts and accessories.",
      "preview":"facilities/garage_servicestation.jpg",
      "pickUpSpotNames":["belascoGarage_parking"],
      "dropOffSpotNames":["belascoGarage_parking"],
      "trailerSpotNames":["belascoGarage_trailer"],
      "sitesFile":"mechanics.sites.json",
      "logisticTypesProvided":["parcel","mechanicalParts","vehNeedsRepair","vehForPrivate","vehRepairFinished"],
      "logisticTypesReceived":["mechanicalParts", "parcel", "food","vehNeedsRepair"],
      "logisticMaxItems":20,
      "logisticGenerators":[
        {
          "type":"parcelProvider",
          "logisticTypes":["mechanicalParts"],
          "min":1,
          "max":2,
          "slotsMax":8,
          "interval":60
        }, {
          "type":"parcelProvider",
          "logisticTypes":["mechanicalParts"],
          "min":1,
          "max":1,
          "slotsMin":8,
          "interval":60
        }, {
          "type":"parcelReceiver",
          "logisticTypes":["parcel"],
          "min":0,
          "max":1,
          "interval":60
        }, {
          "type":"parcelReceiver",
          "logisticTypes":["food"],
          "min":-1,
          "max":1,
          "interval":60
        },

        {
          "type":"vehOfferProvider",
          "interval":60,
          "min":0,
          "max": 3,
          "offerDuration":{"min":300,"max":900},
          "filter":"junkerVehFilter",
          "logisticTypes":["vehNeedsRepair","vehForPrivate","vehRepairFinished"],
        },
        {
          "type":"vehOfferProvider",
          "interval":60,
          "min":0,
          "max": 3,
          "offerDuration":{"min":300,"max":900},
          "filter":"smallVehFilter",
          "logisticTypes":["vehNeedsRepair","vehForPrivate"],
        },
      ],
    },
    {
      "id":"fastAutomotive",
      "name":"Fast Automotive",
      "description":"Ships and receives car parts and accessories.",
      "preview":"previews/fastAutomotive.jpg",
      "pickUpSpotNames":["fastAutomotive_parking"],
      "dropOffSpotNames":["fastAutomotive_parking"],
      "trailerSpotNames":["fastAutomotive_trailer"],
      "sitesFile":"mechanics.sites.json",
      "logisticTypesProvided":["parcel","mechanicalParts","vehNeedsRepair","vehForPrivate","vehRepairFinished"],
      "logisticTypesReceived":["mechanicalParts", "parcel", "food","vehNeedsRepair","vehLargeTruck"],
      "logisticMaxItems":20,
      "logisticGenerators":[
        {
          "type":"parcelProvider",
          "logisticTypes":["mechanicalParts"],
          "min":1,
          "max":2,
          "slotsMax":8,
          "interval":60
        }, {
          "type":"parcelProvider",
          "logisticTypes":["mechanicalParts"],
          "min":1,
          "max":1,
          "slotsMin":8,
          "interval":60
        }, {
          "type":"parcelReceiver",
          "logisticTypes":["parcel"],
          "min":0,
          "max":1,
          "interval":60
        }, {
          "type":"parcelReceiver",
          "logisticTypes":["food"],
          "min":-1,
          "max":1,
          "interval":60
        },
        {
          "type":"vehOfferProvider",
          "interval":60,
          "min":0,
          "max": 2,
          "offerDuration":{"min":300,"max":900},
          "filter":"customizedVehFilter",
          "logisticTypes":["vehNeedsRepair","vehForPrivate","vehRepairFinished"],
        },
        {
          "type":"vehOfferProvider",
          "interval":60,
          "min":0,
          "max": 2,
          "offerDuration":{"min":300,"max":900},
          "filter":"exoticVehFilter",
          "logisticTypes":["vehNeedsRepair","vehForPrivate","vehRepairFinished"],
        },

      ],

    },
    {
      "id":"exhaustShop",
      "name":"Exhaust Shop",
      "description":"Ships and receives car parts and accessories.",
      "preview":"previews/exhaustShop.jpg",
      "pickUpSpotNames":["exhaustShop_parking"],
      "dropOffSpotNames":["exhaustShop_parking"],
      "trailerSpotNames":["exhaustShop_trailer"],
      "sitesFile":"mechanics.sites.json",
      "logisticTypesProvided":["parcel","mechanicalParts","vehNeedsRepair","vehForPrivate","vehRepairFinished"],
      "logisticTypesReceived":["mechanicalParts", "parcel", "food","vehNeedsRepair","vehLargeTruck","vehLargeTruckNeedsRepair"],
      "logisticMaxItems":20,
      "logisticGenerators":[
        {
          "type":"parcelProvider",
          "logisticTypes":["mechanicalParts"],
          "min":1,
          "max":2,
          "slotsMax":8,
          "interval":60
        }, {
          "type":"parcelProvider",
          "logisticTypes":["mechanicalParts"],
          "min":1,
          "max":1,
          "slotsMin":8,
          "interval":60
        }, {
          "type":"parcelReceiver",
          "logisticTypes":["parcel"],
          "min":0,
          "max":1,
          "interval":60
        }, {
          "type":"parcelReceiver",
          "logisticTypes":["food"],
          "min":-1,
          "max":1,
          "interval":60
        },

        {
          "type":"vehOfferProvider",
          "interval":60,
          "min":0,
          "max": 3,
          "offerDuration":{"min":300,"max":900},
          "filter":"junkerVehFilter",
          "logisticTypes":["vehNeedsRepair","vehForPrivate","vehRepairFinished"],
        },
        {
          "type":"vehOfferProvider",
          "interval":60,
          "min":0,
          "max": 3,
          "offerDuration":{"min":300,"max":900},
          "filter":"smallVehFilter",
          "logisticTypes":["vehNeedsRepair","vehForPrivate"],
        },
        {
          "type":"vehOfferProvider",
          "interval":60,
          "min":0,
          "max": 1,
          "offerDuration":{"min":300,"max":900},
          "filter":"customizedVehFilter",
          "logisticTypes":["vehNeedsRepair","vehForPrivate","vehRepairFinished"],
        }
      ],

    },
    {
      "id":"torresTires",
      "name":"Torres Tires",
      "description":"Ships and receives car parts and accessories.",
      "preview":"previews/torresTires.jpg",
      "pickUpSpotNames":["torresTires_parking"],
      "dropOffSpotNames":["torresTires_parking"],
      "trailerSpotNames":["torresTires_trailer"],
      "sitesFile":"mechanics.sites.json",
      "logisticTypesProvided":["parcel","mechanicalParts","vehNeedsRepair","vehForPrivate","vehRepairFinished"],
      "logisticTypesReceived":["mechanicalParts", "parcel", "food","vehNeedsRepair","vehLargeTruck","vehLargeTruckNeedsRepair"],
      "logisticMaxItems":20,
      "logisticGenerators":[
        {
          "type":"parcelProvider",
          "logisticTypes":["mechanicalParts"],
          "min":1,
          "max":2,
          "slotsMax":8,
          "interval":60
        }, {
          "type":"parcelProvider",
          "logisticTypes":["mechanicalParts"],
          "min":1,
          "max":1,
          "slotsMin":8,
          "interval":60
        }, {
          "type":"parcelReceiver",
          "logisticTypes":["parcel"],
          "min":0,
          "max":1,
          "interval":60
        }, {
          "type":"parcelReceiver",
          "logisticTypes":["food"],
          "min":-1,
          "max":1,
          "interval":60
        },

        {
          "type":"vehOfferProvider",
          "interval":60,
          "min":0,
          "max": 3,
          "offerDuration":{"min":300,"max":900},
          "filter":"junkerVehFilter",
          "logisticTypes":["vehNeedsRepair","vehForPrivate","vehRepairFinished"],
        },
        {
          "type":"vehOfferProvider",
          "interval":60,
          "min":0,
          "max": 3,
          "offerDuration":{"min":300,"max":900},
          "filter":"smallVehFilter",
          "logisticTypes":["vehNeedsRepair","vehForPrivate"],
        },
        {
          "type":"vehOfferProvider",
          "interval":60,
          "min":0,
          "max": 1,
          "offerDuration":{"min":300,"max":900},
          "filter":"customizedVehFilter",
          "logisticTypes":["vehNeedsRepair","vehForPrivate","vehRepairFinished"],
        },
      ],

    },
    {
      "id":"smashAutoRepairs",
      "name":"Smash Auto Repairs",
      "description":"Ships and receives car parts and accessories.",
      "preview":"previews/smashAutoRepairs.jpg",
      "pickUpSpotNames":["smashAutoRepairs_parking"],
      "dropOffSpotNames":["smashAutoRepairs_parking"],
      "trailerSpotNames":["smashAutoRepairs_trailer"],
      "sitesFile":"mechanics.sites.json",
      "logisticTypesProvided":["parcel","mechanicalParts","vehNeedsRepair","vehForPrivate","vehRepairFinished"],
      "logisticTypesReceived":["mechanicalParts", "parcel", "food","vehNeedsRepair"],
      "logisticMaxItems":20,
      "logisticGenerators":[
        {
          "type":"parcelProvider",
          "logisticTypes":["mechanicalParts"],
          "min":1,
          "max":2,
          "slotsMax":8,
          "interval":60
        }, {
          "type":"parcelProvider",
          "logisticTypes":["mechanicalParts"],
          "min":1,
          "max":1,
          "slotsMin":8,
          "interval":60
        }, {
          "type":"parcelReceiver",
          "logisticTypes":["parcel"],
          "min":0,
          "max":1,
          "interval":60
        }, {
          "type":"parcelReceiver",
          "logisticTypes":["food"],
          "min":-1,
          "max":1,
          "interval":60
        },

        {
          "type":"vehOfferProvider",
          "interval":60,
          "min":0,
          "max": 3,
          "offerDuration":{"min":300,"max":900},
          "filter":"junkerVehFilter",
          "logisticTypes":["vehNeedsRepair","vehForPrivate","vehRepairFinished"],
        },
        {
          "type":"vehOfferProvider",
          "interval":60,
          "min":0,
          "max": 3,
          "offerDuration":{"min":300,"max":900},
          "filter":"smallVehFilter",
          "logisticTypes":["vehNeedsRepair","vehForPrivate"],
        },
        {
          "type":"vehOfferProvider",
          "interval":60,
          "min":0,
          "max": 1,
          "offerDuration":{"min":300,"max":900},
          "filter":"customizedVehFilter",
          "logisticTypes":["vehNeedsRepair","vehForPrivate","vehRepairFinished"],
        },
      ],

    },
    {
      "id":"jerryRigs",
      "name":"Jerry Rigs",
      "description":"Ships and receives car parts and accessories.",
      "preview":"previews/jerryRigs.jpg",
      "pickUpSpotNames":["jerryRigs_parking"],
      "dropOffSpotNames":["jerryRigs_parking"],
      "trailerSpotNames":["jerryRigs_trailer"],
      "sitesFile":"mechanics.sites.json",
      "logisticTypesProvided":["parcel","mechanicalParts","vehNeedsRepair","vehForPrivate","vehRepairFinished"],
      "logisticTypesReceived":["mechanicalParts", "parcel", "food","vehNeedsRepair"],
      "logisticMaxItems":20,
      "logisticGenerators":[
        {
          "type":"parcelProvider",
          "logisticTypes":["mechanicalParts"],
          "min":1,
          "max":2,
          "slotsMax":8,
          "interval":60
        }, {
          "type":"parcelProvider",
          "logisticTypes":["mechanicalParts"],
          "min":1,
          "max":1,
          "slotsMin":8,
          "interval":60
        }, {
          "type":"parcelReceiver",
          "logisticTypes":["parcel"],
          "min":0,
          "max":1,
          "interval":60
        }, {
          "type":"parcelReceiver",
          "logisticTypes":["food"],
          "min":-1,
          "max":1,
          "interval":60
        },

        {
          "type":"vehOfferProvider",
          "interval":60,
          "min":0,
          "max": 1,
          "offerDuration":{"min":300,"max":900},
          "filter":"junkerVehFilter",
          "logisticTypes":["vehNeedsRepair","vehForPrivate","vehRepairFinished"],
        },
        {
          "type":"vehOfferProvider",
          "interval":60,
          "min":0,
          "max": 3,
          "offerDuration":{"min":300,"max":900},
          "filter":"smallVehFilter",
          "logisticTypes":["vehNeedsRepair","vehForPrivate"],
        },
        {
          "type":"vehOfferProvider",
          "interval":60,
          "min":0,
          "max": 3,
          "offerDuration":{"min":300,"max":900},
          "filter":"customizedVehFilter",
          "logisticTypes":["vehNeedsRepair","vehForPrivate","vehRepairFinished"],
        },
      ],

    },
    {
      "id":"shuffleboardLogistics",
      "name":"Shuffleboard Logistics",
      "description":"Ships and receives car parts and accessories.",
      "preview":"previews/shuffleboardLogistics.jpg",
      "pickUpSpotNames":["shuffleboardLogistics_parking"],
      "dropOffSpotNames":["shuffleboardLogistics_parking"],
      "trailerSpotNames":["shuffleboardLogistics_trailer"],
      "sitesFile":"mechanics.sites.json",
      "logisticTypesProvided":["parcel","mechanicalParts","vehNeedsRepair","vehForPrivate","vehRepairFinished", "vehDeliveryAmbulance","vehLargeTruck","vehLargeTruckNeedsRepair"],
      "logisticTypesReceived":["mechanicalParts", "parcel", "food","vehNeedsRepair","vehLargeTruck","vehLargeTruckNeedsRepair"],
      "logisticMaxItems":20,
      "logisticGenerators":[
        {
          "type":"parcelProvider",
          "logisticTypes":["mechanicalParts"],
          "min":1,
          "max":2,
          "slotsMax":8,
          "interval":60
        }, {
          "type":"parcelProvider",
          "logisticTypes":["mechanicalParts"],
          "min":1,
          "max":1,
          "slotsMin":8,
          "interval":60
        }, {
          "type":"parcelReceiver",
          "logisticTypes":["parcel"],
          "min":0,
          "max":1,
          "interval":60
        }, {
          "type":"parcelReceiver",
          "logisticTypes":["food"],
          "min":-1,
          "max":1,
          "interval":60
        },
        {
          "type":"vehOfferProvider",
          "interval":60,
          "min":-1,
          "max": 1,
          "offerDuration":{"min":300,"max":300},
          "filter":"ambulanceFleetVehFilter",
          "logisticTypes":["vehDeliveryAmbulance"],
        },
        {
          "type":"vehOfferProvider",
          "interval":60,
          "min":1,
          "max": 3,
          "offerDuration":{"min":300,"max":300},
          "filter":"largeVehFilter",
          "logisticTypes":["vehLargeTruck","vehLargeTruckNeedsRepair"],
        },
        {
          "type":"vehOfferProvider",
          "interval":60,
          "min":0,
          "max": 2,
          "offerDuration":{"min":300,"max":300},
          "filter":"fleetLargeVehFilter",
          "logisticTypes":["vehLargeTruck"],
        },
      ],

    },

    // Dealerships
    {
      "id":"quarrysideAutoSales",
      "name":"Quarryside Auto Sales",
      "description":"Ships and receives car parts and accessories.",
      "preview":"facilities/quarryside_dealership.jpg",
      "pickUpSpotNames":["quarrysideAutoSales_parking"],
      "dropOffSpotNames":["quarrysideAutoSales_parking"],
      "trailerSpotNames":["quarrysideAutoSales_trailer"],
      "sitesFile":"mechanics.sites.json",
      "logisticTypesProvided":["parcel","mechanicalParts","rareMechanicalParts","vehNeedsRepair","vehForPrivate","vehRepairFinished"],
      "logisticTypesReceived":["mechanicalParts","rareMechanicalParts" "parcel", "food","vehRepairFinished"],
      "logisticMaxItems":20,
      "logisticGenerators":[
        {
          "type":"parcelProvider",
          "logisticTypes":["mechanicalParts"],
          "min":1,
          "max":2,
          "slotsMax":8,
          "interval":60
        }, {
          "type":"parcelProvider",
          "logisticTypes":["mechanicalParts"],
          "min":1,
          "max":1,
          "slotsMin":8,
          "interval":60
        }, {
          "type":"parcelReceiver",
          "logisticTypes":["parcel"],
          "min":0,
          "max":1,
          "interval":60
        }, {
          "type":"parcelReceiver",
          "logisticTypes":["food"],
          "min":-1,
          "max":1,
          "interval":60
        },
        {
          "type":"vehOfferProvider",
          "interval":60,
          "min":0,
          "max": 1,
          "offerDuration":{"min":300,"max":900},
          "filter":"junkerVehFilter",
          "logisticTypes":["vehNeedsRepair","vehForPrivate","vehRepairFinished"],
        },
        {
          "type":"vehOfferProvider",
          "interval":60,
          "min":0,
          "max": 3,
          "offerDuration":{"min":300,"max":900},
          "filter":"smallVehFilter",
          "logisticTypes":["vehNeedsRepair","vehForPrivate"],
        },

      ],


    },
    {
      "id":"belascoAuto",
      "name":"Belasco Auto",
      "description":"Ships and receives car parts and accessories.",
      "preview":"facilities/belasco_auto_dealership.jpg",
      "pickUpSpotNames":["belascoAuto_parking"],
      "dropOffSpotNames":["belascoAuto_parking"],
      "trailerSpotNames":["belascoAuto_trailer"],
      "sitesFile":"mechanics.sites.json",
      "logisticTypesProvided":["parcel","mechanicalParts","rareMechanicalParts","vehNeedsRepair","vehForPrivate"],
      "logisticTypesReceived":["mechanicalParts","rareMechanicalParts" "parcel", "food","trailer","vehRepairFinished"],
      "logisticMaxItems":20,
      "logisticGenerators":[
        {
          "type":"parcelProvider",
          "logisticTypes":["mechanicalParts"],
          "min":1,
          "max":2,
          "slotsMax":8,
          "interval":60
        }, {
          "type":"parcelProvider",
          "logisticTypes":["mechanicalParts"],
          "min":1,
          "max":1,
          "slotsMin":8,
          "interval":60
        }, {
          "type":"parcelReceiver",
          "logisticTypes":["parcel"],
          "min":0,
          "max":1,
          "interval":60
        }, {
          "type":"parcelReceiver",
          "logisticTypes":["food"],
          "min":-1,
          "max":1,
          "interval":60
        },


        {
          "type":"vehOfferProvider",
          "interval":60,
          "min":0,
          "max": 3,
          "offerDuration":{"min":300,"max":900},
          "filter":"smallVehFilter",
          "logisticTypes":["vehNeedsRepair","vehForPrivate"],
        },
        {
          "type":"vehOfferProvider",
          "interval":60,
          "min":0,
          "max": 3,
          "offerDuration":{"min":300,"max":900},
          "filter":"fleetVehFilter",
          "logisticTypes":["vehNeedsRepair","vehForPrivate"],
        },

      ],

      
    },
    {
      "id":"jeffersonMotors",
      "name":"Jefferson Motors",
      "description":"Ships and receives car parts and accessories.",
      "preview":"facilities/jefferson_dealership.jpg",
      "pickUpSpotNames":["jeffersonMotors_parking"],
      "dropOffSpotNames":["jeffersonMotors_parking"],
      "trailerSpotNames":["jeffersonMotors_trailer"],
      "sitesFile":"mechanics.sites.json",
      "logisticTypesProvided":["parcel","mechanicalParts","rareMechanicalParts","vehNeedsRepair","vehForPrivate","vehDeliveryPolice"],
      "logisticTypesReceived":["mechanicalParts","rareMechanicalParts" "parcel", "food","trailer","vehRepairFinished"],
      "logisticMaxItems":20,
      "logisticGenerators":[
        {
          "type":"parcelProvider",
          "logisticTypes":["mechanicalParts"],
          "min":1,
          "max":2,
          "slotsMax":8,
          "interval":60
        }, {
          "type":"parcelProvider",
          "logisticTypes":["mechanicalParts"],
          "min":1,
          "max":1,
          "slotsMin":8,
          "interval":60
        }, {
          "type":"parcelReceiver",
          "logisticTypes":["parcel"],
          "min":0,
          "max":1,
          "interval":60
        }, {
          "type":"parcelReceiver",
          "logisticTypes":["food"],
          "min":-1,
          "max":1,
          "interval":60
        },


        {
          "type":"vehOfferProvider",
          "interval":60,
          "min":0,
          "max": 3,
          "offerDuration":{"min":300,"max":900},
          "filter":"fleetVehFilter",
          "logisticTypes":["vehNeedsRepair","vehForPrivate"],
        },
        {
          "type":"vehOfferProvider",
          "interval":60,
          "min":0,
          "max": 3,
          "offerDuration":{"min":300,"max":900},
          "filter":"smallVehFilter",
          "logisticTypes":["vehNeedsRepair","vehForPrivate"],
        },
        {
          "type":"vehOfferProvider",
          "interval":60,
          "min":-1,
          "max": 1,
          "offerDuration":{"min":300,"max":300},
          "filter":"policeFleetVehFilter",
          "logisticTypes":["vehDeliveryPolice"],
        },

      ],

    },
    {
      "id":"richsMotorCompany",
      "name":"Rich's Motor Company",
      "description":"Ships and receives car parts and accessories.",
      "preview":"facilities/richsmotorcompany_dealership.jpg",
      "pickUpSpotNames":["richsMotorCompany_parking"],
      "dropOffSpotNames":["richsMotorCompany_parking"],
      "trailerSpotNames":["richsMotorCompany_trailer"],
      "sitesFile":"mechanics.sites.json",
      "logisticTypesProvided":["parcel","mechanicalParts","rareMechanicalParts","vehNeedsRepair","vehForPrivate"],
      "logisticTypesReceived":["mechanicalParts","rareMechanicalParts" "parcel", "food","trailer","vehRepairFinished"],
      "logisticMaxItems":20,
      "logisticGenerators":[
        {
          "type":"parcelProvider",
          "logisticTypes":["mechanicalParts"],
          "min":1,
          "max":2,
          "slotsMax":8,
          "interval":60
        }, {
          "type":"parcelProvider",
          "logisticTypes":["mechanicalParts"],
          "min":1,
          "max":1,
          "slotsMin":8,
          "interval":60
        }, {
          "type":"parcelReceiver",
          "logisticTypes":["parcel"],
          "min":0,
          "max":1,
          "interval":60
        }, {
          "type":"parcelReceiver",
          "logisticTypes":["food"],
          "min":-1,
          "max":1,
          "interval":60
        },



        {
          "type":"vehOfferProvider",
          "interval":60,
          "min":0,
          "max": 2,
          "offerDuration":{"min":300,"max":900},
          "filter":"customizedVehFilter",
          "logisticTypes":["vehNeedsRepair","vehForPrivate"],
        },
        {
          "type":"vehOfferProvider",
          "interval":60,
          "min":0,
          "max": 3,
          "offerDuration":{"min":300,"max":900},
          "filter":"exoticVehFilter",
          "logisticTypes":["vehNeedsRepair","vehForPrivate"],
        },
      ],

    }
  ]
}